readme_maker_py-0.2.5.dist-info/licenses/LICENSE
readmemaker/__init__.py
readmemaker/my_module.py
readme_maker_py-0.2.5.dist-info/METADATA
readme_maker_py-0.2.5.dist-info/WHEEL
readme_maker_py-0.2.5.dist-info/entry_points.txt
readme_maker_py-0.2.5.dist-info/top_level.txt
readme_maker_py-0.2.5.dist-info/RECORD
