Metadata-Version: 2.4
Name: readme-maker-py
Version: 0.2.5
Summary: Github readme file maker
Home-page: https://github.com/Antriksh006/readme-file-maker
Author: antrishh
Author-email: antrikshg007@gmail.com
Classifier: Programming Language :: Python :: 3
Classifier: License :: OSI Approved :: MIT License
Classifier: Operating System :: OS Independent
Requires-Python: >=3.6
License-File: LICENSE
Requires-Dist: groq
Requires-Dist: PyGithub
Requires-Dist: nbformat
Requires-Dist: nbconvert
Dynamic: author
Dynamic: author-email
Dynamic: classifier
Dynamic: description-content-type
Dynamic: home-page
Dynamic: license-file
Dynamic: requires-dist
Dynamic: requires-python
Dynamic: summary
